common/__init__.py
common/__main__.py
common/cli.py
common_cli_tool-0.2.1.dist-info/METADATA
common_cli_tool-0.2.1.dist-info/WHEEL
common_cli_tool-0.2.1.dist-info/entry_points.txt
common_cli_tool-0.2.1.dist-info/top_level.txt
common_cli_tool-0.2.1.dist-info/RECORD
