Metadata-Version: 2.4
Name: common-cli-tool
Version: 0.2.1
Summary: A CLI tool to help study for CompTIA A+ exams
Author: Omar Zebibo
Requires-Dist: colorama
Requires-Dist: tabulate
Dynamic: author
Dynamic: requires-dist
Dynamic: summary
